feynlab_sensor_shield/__init__.py
feynlab_sensor_shield/apds9960.py
feynlab_sensor_shield/bme280.py
feynlab_sensor_shield/mma8491q.py
feynlab_sensor_shield/relay_controller.py
feynlab_sensor_shield/veml6075.py
feynLab_sensor_shield-1.3.2.dist-info/LICENSE
feynLab_sensor_shield-1.3.2.dist-info/METADATA
feynLab_sensor_shield-1.3.2.dist-info/WHEEL
feynLab_sensor_shield-1.3.2.dist-info/top_level.txt
feynLab_sensor_shield-1.3.2.dist-info/RECORD
